matfin/__init__.py
matfin/freq.py
matfin/interest.py
matfin-0.0.2.dist-info/LICENSE
matfin-0.0.2.dist-info/METADATA
matfin-0.0.2.dist-info/WHEEL
matfin-0.0.2.dist-info/top_level.txt
matfin-0.0.2.dist-info/RECORD
